mypypackage/__init__.py
mypypackage/mypypackage.py
mypypackage-0.1.0.dist-info/LICENSE
mypypackage-0.1.0.dist-info/WHEEL
mypypackage-0.1.0.dist-info/METADATA
mypypackage-0.1.0.dist-info/RECORD
