Metadata-Version: 2.1
Name: mypypackage
Version: 0.1.0
Summary: This package was created for Assignment 1 DSCI 524
License: MIT
Author: Nash Makhija
Author-email: naurattan.makhija@gmail.com
Requires-Python: >=3.8,<4.0
Classifier: License :: OSI Approved :: MIT License
Classifier: Programming Language :: Python :: 3
Classifier: Programming Language :: Python :: 3.8
Classifier: Programming Language :: Python :: 3.9
Requires-Dist: pandas (>=1.2.2,<2.0.0)
